regml_task_registry_hardcoded/__init__.py
regml_task_registry_hardcoded/tasks/__init__.py
regml_task_registry_hardcoded/tasks/llmchat/__init__.py
regml_task_registry_hardcoded/tasks/llmchat/registry.py
regml_task_registry_hardcoded-0.0.1.dist-info/METADATA
regml_task_registry_hardcoded-0.0.1.dist-info/WHEEL
regml_task_registry_hardcoded-0.0.1.dist-info/RECORD
